gnr/__init__.py
gnr/_modidx.py
gnr/fn.py
gnr/mock.py
gnr/op.py
gnr/static.py
gnr/utils.py
gnr-0.0.4.dist-info/LICENSE
gnr-0.0.4.dist-info/METADATA
gnr-0.0.4.dist-info/WHEEL
gnr-0.0.4.dist-info/entry_points.txt
gnr-0.0.4.dist-info/top_level.txt
gnr-0.0.4.dist-info/RECORD
