Metadata-Version: 2.1
Name: gnr
Version: 0.0.4
Summary: granger causality analysis
Home-page: https://github.com/dsm-72/gnr
Author: dsm-72
Author-email: sumner.magruder@yale.edu
License: Apache Software License 2.0
Keywords: nbdev jupyter notebook python
Classifier: Development Status :: 4 - Beta
Classifier: Intended Audience :: Developers
Classifier: Natural Language :: English
Classifier: Programming Language :: Python :: 3.7
Classifier: Programming Language :: Python :: 3.8
Classifier: Programming Language :: Python :: 3.9
Classifier: Programming Language :: Python :: 3.10
Classifier: License :: OSI Approved :: Apache Software License
Requires-Python: >=3.7
License-File: LICENSE
Requires-Dist: atyp
Requires-Dist: statsmodels
Provides-Extra: dev
Requires-Dist: pandas ; extra == 'dev'
Requires-Dist: seaborn ; extra == 'dev'
Requires-Dist: scikit-learn ; extra == 'dev'
Requires-Dist: numpy ; extra == 'dev'
